MANIFEST.in
README.rst
setup.py
conclas/__init__.py
conclas/api.py
conclas.egg-info/PKG-INFO
conclas.egg-info/SOURCES.txt
conclas.egg-info/dependency_links.txt
conclas.egg-info/requires.txt
conclas.egg-info/top_level.txt
conclas/core/__init__.py
conclas/core/conclas_response.py
conclas/core/request.py
conclas/exceptions/__init__.py
conclas/exceptions/api_custom_exceptions.py
conclas/exceptions/client_exceptions.py
conclas/utils/__init__.py
conclas/utils/json_maker.py