Metadata-Version: 1.1
Name: conclas
Version: 0.1.1
Summary: The ConClas is a client written in Python to use the service Conclas.
Home-page: https://github.com/s1mbi0se/conclas/tree/develop/conclas/clients/pyconclas
Author: ConClas
Author-email: hello@conclas.com
License: BSD
Keywords: conclas machine learning pyconclas
Platform: UNKNOWN
Classifier: Programming Language :: Python :: 2.7
Classifier: Topic :: Scientific/Engineering :: Information Analysis
Classifier: Topic :: Text Processing :: Linguistic
